pg_es_fdw/__init__.py
pg_es_fdw/columns.py
pg_es_fdw/fdw.py
pg_es_fdw/options.py
pg_es_fdw-0.12.0.dist-info/LICENSE
pg_es_fdw-0.12.0.dist-info/METADATA
pg_es_fdw-0.12.0.dist-info/WHEEL
pg_es_fdw-0.12.0.dist-info/RECORD
