Metadata-Version: 2.1
Name: pg-es-fdw
Version: 0.12.0
Summary: Connect PostgreSQL and Elastic Search with this Foreign Data Wrapper
Home-page: https://github.com/matthewfranglen/postgres-elasticsearch-fdw
License: MIT
Keywords: postgresql,postgres,elasticsearch,es,fdw
Author: Matthew Franglen
Author-email: matthew@franglen.org
Classifier: License :: OSI Approved :: MIT License
Classifier: Programming Language :: Python :: 2
Classifier: Programming Language :: Python :: 2.7
Classifier: Programming Language :: Python :: 3
Classifier: Programming Language :: Python :: 3.4
Classifier: Programming Language :: Python :: 3.5
Classifier: Programming Language :: Python :: 3.6
Classifier: Programming Language :: Python :: 3.7
Classifier: Programming Language :: Python :: 3.8
Classifier: Programming Language :: Python :: 3.9
Classifier: Programming Language :: Python :: 3.10
Classifier: Programming Language :: Python :: 3.11
Classifier: Programming Language :: Python :: 3.12
Project-URL: Repository, https://github.com/matthewfranglen/postgres-elasticsearch-fdw
Project-URL: download, https://github.com/matthewfranglen/postgres-elasticsearch-fdw/archive/0.12.0.zip
